guacamole_cli
