Metadata-Version: 1.1
Name: guacamole-cli
Version: 0.3.1
Summary: Guacamole command line interface
Home-page: https://github.com/Antojitos/guacamole-cli
Author: Pablo SEMINARIO
Author-email: pablo@seminar.io
License: GNU General Public License v3 (GPLv3)
Download-URL: https://github.com/Antojitos/guacamole-cli/archive/0.3.1.tar.gz
Keywords: cli,guacamole
Platform: UNKNOWN
Classifier: Development Status :: 5 - Production/Stable
Classifier: Environment :: Console
Classifier: License :: OSI Approved :: GNU General Public License v3 (GPLv3)
Classifier: Operating System :: OS Independent
Classifier: Programming Language :: Python :: 2.7
Classifier: Programming Language :: Python :: 3
Classifier: Topic :: Internet :: WWW/HTTP
